nbhtml/__init__.py
nbhtml/read.py
nbhtml/saving.tpl
nbhtml/write.py
nbhtml-0.1.dist-info/WHEEL
nbhtml-0.1.dist-info/METADATA
nbhtml-0.1.dist-info/RECORD
