Metadata-Version: 1.2
Name: nbhtml
Version: 0.1
Summary: Save & load Jupyter notebooks as HTML
Home-page: https://github.com/takluyver/nbhtml
License: UNKNOWN
Author: Thomas Kluyver
Author-email: thomas@kluyver.me.uk
Requires-Python: >=3.4
Classifier: License :: OSI Approved :: BSD License
Classifier: Programming Language :: Python :: 3
Classifier: Topic :: Text Processing :: Markup :: HTML
Requires-Dist: nbformat
Requires-Dist: nbconvert
Requires-Dist: lxml
